j_html_pdf/__init__.py
j_html_pdf/html_simple.py
j_html_pdf/test_html_simple.py
j_html_pdf-1.0.0.dist-info/LICENSE.txt
j_html_pdf-1.0.0.dist-info/METADATA
j_html_pdf-1.0.0.dist-info/WHEEL
j_html_pdf-1.0.0.dist-info/top_level.txt
j_html_pdf-1.0.0.dist-info/RECORD
