Metadata-Version: 2.1
Name: j-html-pdf
Version: 1.0.0
Summary: Wrapper around weasyprint.
Home-page: https://github.com/JWDT/j_html_pdf
Author: jdev
Author-email: pypi@johken.uk
License: The Unlicense
Platform: UNKNOWN
